fastapi_swagger_dark/__init__.py
fastapi_swagger_dark/swagger_ui_dark.css
fastapi_swagger_dark/swagger_ui_dark.min.css
fastapi_swagger_dark-0.0.9.dist-info/METADATA
fastapi_swagger_dark-0.0.9.dist-info/WHEEL
fastapi_swagger_dark-0.0.9.dist-info/licenses/LICENSE
fastapi_swagger_dark-0.0.9.dist-info/RECORD
