Metadata-Version: 2.4
Name: fastapi-swagger-dark
Version: 0.0.9
Summary: FastAPI plugin to add dark theme swagger docs.
Project-URL: homepage, https://github.com/NRWLDev/fastapi-swagger-dark/
Author-email: Daniel Edgecombe <daniel@nrwl.co>
License-Expression: Apache-2.0
License-File: LICENSE
Keywords: exception,handler,starlette,webdev
Classifier: Development Status :: 4 - Beta
Classifier: Environment :: Web Environment
Classifier: Framework :: FastAPI
Classifier: Intended Audience :: Developers
Classifier: License :: OSI Approved :: Apache Software License
Classifier: Operating System :: OS Independent
Classifier: Programming Language :: Python
Classifier: Programming Language :: Python :: 3
Classifier: Programming Language :: Python :: 3 :: Only
Classifier: Programming Language :: Python :: 3.9
Classifier: Programming Language :: Python :: 3.10
Classifier: Programming Language :: Python :: 3.11
Classifier: Programming Language :: Python :: 3.12
Classifier: Topic :: Internet
Classifier: Topic :: Utilities
Requires-Python: >=3.9
Provides-Extra: dev
Requires-Dist: changelog-gen>=0.12; extra == 'dev'
Requires-Dist: fastapi; extra == 'dev'
Requires-Dist: pre-commit>=3.7.1; extra == 'dev'
Requires-Dist: pytest-asyncio>=0.21; extra == 'dev'
Requires-Dist: pytest-cov>=4.1.0; extra == 'dev'
Requires-Dist: pytest-httpx>=0.26.0; extra == 'dev'
Requires-Dist: pytest-random-order>=1.0; extra == 'dev'
Requires-Dist: pytest>=7.4.3; extra == 'dev'
Requires-Dist: rcssmin; extra == 'dev'
Requires-Dist: ruff>=0.6.4; extra == 'dev'
